LICENSE
README.md
setup.py
pyoppleio/Message.py
pyoppleio/OppleDevice.py
pyoppleio/OppleLightDevice.py
pyoppleio/__init__.py
pyoppleio/__main__.py
pyoppleio/const.py
pyoppleio/search.py
pyoppleio.egg-info/PKG-INFO
pyoppleio.egg-info/SOURCES.txt
pyoppleio.egg-info/dependency_links.txt
pyoppleio.egg-info/entry_points.txt
pyoppleio.egg-info/requires.txt
pyoppleio.egg-info/top_level.txt