Metadata-Version: 2.1
Name: pyoppleio
Version: 1.0.7
Summary: Python library for interfacing with opple mobile control light
Home-page: https://github.com/jedmeng/python-oppleio
Author: jedmeng
Author-email: jedm@jedm.cn
License: MIT
Keywords: opple,iot
Platform: any
Requires-Python: >=3.5
License-File: LICENSE
